[
  {
    "activityid": "1",
    "name": "团体音乐节录制",
    "category": 1,
    "conditionid": 0,
    "costfp": 100,
    "costfpfirst": 0,
    "costitemid": 0,
    "costitemcount": 0,
    "outputposttype1": 401,
    "outputposttype2": 101,
    "drawcount": 1,
    "refreshmarket": 0,
    "tutorialonly": 0,
    "sort": 1,
    "stexplow": 5,
    "stexpmid": 10,
    "stexphigh": 15,
    "opinionlock": 0,
    "winrate": 50,
    "winratefirst": 1,
    "granttagid": "tag_music",
    "grantcountfirst": 2,
    "grantcountrepeat": 1,
    "feedkeycount": 1,
    "feedadvancedcount": 2,
    "feednormalcount": 4,
    "openingonly": 1,
    "needfans": 0,
    "needkeyposts": 0,
    "demoid": "demo_open"
  },
  {
    "activityid": "2",
    "name": "音乐节·二排应援",
    "category": 2,
    "conditionid": 0,
    "costfp": 150,
    "costfpfirst": 150,
    "costitemid": 0,
    "costitemcount": 0,
    "outputposttype1": 401,
    "outputposttype2": 101,
    "drawcount": 1,
    "refreshmarket": 0,
    "tutorialonly": 0,
    "sort": 2,
    "stexplow": 5,
    "stexpmid": 10,
    "stexphigh": 15,
    "opinionlock": 0,
    "winrate": 50,
    "winratefirst": 0,
    "granttagid": "tag_music",
    "grantcountfirst": 2,
    "grantcountrepeat": 1,
    "feedkeycount": 1,
    "feedadvancedcount": 1,
    "feednormalcount": 3,
    "openingonly": 0,
    "needfans": 100,
    "needkeyposts": 0,
    "demoid": "demo"
  },
  {
    "activityid": "3",
    "name": "音乐节·后台代拍",
    "category": 2,
    "conditionid": 0,
    "costfp": 200,
    "costfpfirst": 300,
    "costitemid": 0,
    "costitemcount": 0,
    "outputposttype1": 401,
    "outputposttype2": 101,
    "drawcount": 1,
    "refreshmarket": 0,
    "tutorialonly": 0,
    "sort": 3,
    "stexplow": 5,
    "stexpmid": 10,
    "stexphigh": 15,
    "opinionlock": 0,
    "winrate": 40,
    "winratefirst": 0,
    "granttagid": "tag_music",
    "grantcountfirst": 2,
    "grantcountrepeat": 1,
    "feedkeycount": 1,
    "feedadvancedcount": 2,
    "feednormalcount": 2,
    "openingonly": 0,
    "needfans": 0,
    "needkeyposts": 2,
    "demoid": "demo"
  },
  {
    "activityid": "4",
    "name": "机场接送机1",
    "category": 1,
    "conditionid": 0,
    "costfp": 10,
    "costfpfirst": 10,
    "costitemid": 0,
    "costitemcount": 0,
    "outputposttype1": 401,
    "outputposttype2": 101,
    "drawcount": 1,
    "refreshmarket": 0,
    "tutorialonly": 0,
    "sort": 4,
    "stexplow": 5,
    "stexpmid": 10,
    "stexphigh": 15,
    "opinionlock": 0,
    "winrate": 100,
    "winratefirst": 0,
    "granttagid": "tag_airport",
    "grantcountfirst": 1,
    "grantcountrepeat": 1,
    "feedkeycount": 0,
    "feedadvancedcount": 0,
    "feednormalcount": 3,
    "openingonly": 0,
    "needfans": 0,
    "needkeyposts": 0,
    "demoid": "demo"
  },
  {
    "activityid": "5",
    "name": "机场接送机2",
    "category": 1,
    "conditionid": 0,
    "costfp": 60,
    "costfpfirst": 60,
    "costitemid": 0,
    "costitemcount": 0,
    "outputposttype1": 401,
    "outputposttype2": 101,
    "drawcount": 1,
    "refreshmarket": 0,
    "tutorialonly": 0,
    "sort": 5,
    "stexplow": 5,
    "stexpmid": 10,
    "stexphigh": 15,
    "opinionlock": 0,
    "winrate": 100,
    "winratefirst": 0,
    "granttagid": "tag_airport",
    "grantcountfirst": 1,
    "grantcountrepeat": 1,
    "feedkeycount": 0,
    "feedadvancedcount": 1,
    "feednormalcount": 3,
    "openingonly": 0,
    "needfans": 0,
    "needkeyposts": 0,
    "demoid": "demo"
  },
  {
    "activityid": "6",
    "name": "机场接送机3",
    "category": 1,
    "conditionid": 0,
    "costfp": 120,
    "costfpfirst": 120,
    "costitemid": 0,
    "costitemcount": 0,
    "outputposttype1": 401,
    "outputposttype2": 101,
    "drawcount": 1,
    "refreshmarket": 0,
    "tutorialonly": 0,
    "sort": 6,
    "stexplow": 5,
    "stexpmid": 10,
    "stexphigh": 15,
    "opinionlock": 0,
    "winrate": 80,
    "winratefirst": 0,
    "granttagid": "tag_airport",
    "grantcountfirst": 1,
    "grantcountrepeat": 1,
    "feedkeycount": 0,
    "feedadvancedcount": 1,
    "feednormalcount": 4,
    "openingonly": 0,
    "needfans": 300,
    "needkeyposts": 0,
    "demoid": "demo"
  },
  {
    "activityid": "7",
    "name": "乡下表演1",
    "category": 1,
    "conditionid": 0,
    "costfp": 300,
    "costfpfirst": 400,
    "costitemid": 0,
    "costitemcount": 0,
    "outputposttype1": 401,
    "outputposttype2": 101,
    "drawcount": 1,
    "refreshmarket": 0,
    "tutorialonly": 0,
    "sort": 7,
    "stexplow": 5,
    "stexpmid": 10,
    "stexphigh": 15,
    "opinionlock": 0,
    "winrate": 35,
    "winratefirst": 0,
    "granttagid": "tag_rural",
    "grantcountfirst": 2,
    "grantcountrepeat": 1,
    "feedkeycount": 1,
    "feedadvancedcount": 2,
    "feednormalcount": 3,
    "openingonly": 0,
    "needfans": 0,
    "needkeyposts": 4,
    "demoid": "demo"
  }
]
